{"id":"bernie-moreno","name":"Bernie Moreno","title":"Senator","state":"Ohio","party":"Republican","chamber":"Senate","seniority":"Senior","term_start":"2025-01-03","term_end":"2031-01-03","biography":{"summary":"Bernie Moreno is a Republican United States Senator from Ohio serving since 2025.","early_life":"","education":"","career":""},"photo":{"profile":"https://unitedstates.github.io/images/congress/225x275/M001242.jpg","header":"https://unitedstates.github.io/images/congress/450x550/M001242.jpg"},"contact":{"website":"https://www.moreno.senate.gov","office_address":"284 Russell Senate Office Building, Washington DC 20510","phone":"202-224-2315","social":{"twitter":"https://twitter.com/BernieMoreno","facebook":"https://facebook.com/BernieMoreno","youtube":"https://www.youtube.com/@BernieMoreno","instagram":"https://www.instagram.com/berniemoreno"}},"committees":[{"name":"Appropriations Committee","position":"Member"},{"name":"Armed Services Committee","position":"Member"},{"name":"Banking, Housing, and Urban Affairs Committee","position":"Member"}],"policy_positions":[{"topic":"Economy","stance":"Pro-business"},{"topic":"Labor","stance":"Supports workforce training and jobs growth"},{"topic":"Healthcare","stance":"Market-based reforms to reduce costs"}],"legislation":{"bills_sponsored":[],"recent_votes":[]},"timeline":[{"year":"2025","event":"Assumed office as U.S. Senator for Ohio."},{"year":"2025","event":"Announced priorities including economy, national security, and healthcare."}],"media":{"photos":["https://unitedstates.github.io/images/congress/225x275/M001242.jpg","https://unitedstates.github.io/images/congress/450x550/M001242.jpg"],"videos":[{"title":"Senator Bernie Moreno Official Profile","url":"https://www.youtube.com/watch?v=MorenoOfficial"}]}}